{
  "$insert_id": "5b8930f9-3ba5-44f5-9766-557d652fe50b",
  "$insert_key": null,
  "$schema": null,
  "adid": null,
  "amplitude_attribution_ids": null,
  "amplitude_event_type": null,
  "amplitude_id": 92934234282,
  "app": 100011471,
  "city": "Enfield",
  "client_event_time": "2025-12-23 19:25:16.820000",
  "client_upload_time": "2026-01-02 15:15:13.373000",
  "country": "United States",
  "data": {
    "group_first_event": {},
    "group_ids": {},
    "path": "/2/httpapi",
    "user_properties_updated": true
  },
  "data_type": "event",
  "device_brand": null,
  "device_carrier": null,
  "device_family": "Windows",
  "device_id": "a9f83f39-8cbb-429e-95a7-9bb7a1a15cb0",
  "device_manufacturer": null,
  "device_model": null,
  "device_type": "Windows",
  "dma": "Hartford & New Haven, CT",
  "event_id": 8,
  "event_properties": {},
  "event_time": "2025-12-23 19:25:16.820000",
  "event_type": "session_end",
  "global_user_properties": null,
  "group_properties": {},
  "groups": {},
  "idfa": null,
  "ip_address": "70.181.39.121",
  "is_attribution_event": null,
  "language": "English",
  "library": "amplitude-ts/2.16.1",
  "location_lat": null,
  "location_lng": null,
  "os_name": "Edge",
  "os_version": "143",
  "partner_id": null,
  "paying": null,
  "plan": {},
  "platform": "Web",
  "processed_time": "2026-01-02 15:15:14.826000",
  "region": "Connecticut",
  "sample_rate": null,
  "server_received_time": "2026-01-02 15:15:13.373000",
  "server_upload_time": "2026-01-02 15:15:13.377000",
  "session_id": 1766517916812,
  "source_id": null,
  "start_version": null,
  "user_creation_time": null,
  "user_id": null,
  "user_properties": {},
  "uuid": "36183212-c79c-4544-a44c-6b41122fdda9",
  "version_name": null
}